<?xml version="1.0" encoding="windows-1251"?>

<!--
	Medical Items + Drugs
-->

<string_table>
	
	<string id="st_antirad">
		<text>ѕротиворадиационный препарат</text>
	</string>
	<string id="st_antirad_descr">
		<text>ѕрепарат радиозащитного действи€ Ђћексаминї, широко распространЄнный на территории «оны. ѕри применении вызывает сужение периферических кровеносных сосудов и кислородное голодание, что в данном случае €вл€етс€ средством профилактики и лечени€ лучевой болезни. ’орошо переноситс€ подавл€ющим большинством людей; в отдельных случа€х возможны: лЄгка€ тошнота, головокружение, боли, реже - рвота.\n \n
		%c[ui_gray_3]Ћ≈„≈Ќ»≈:\n
		%c[d_red] Х %c[ui_gray_2] ќтнимает 5% здоровь€ при использовании\n
		%c[ui_gray_3]’ј–ј “≈–»—“» »:\n
		%c[d_blue] Х %c[ui_gray_2] медикамент\n
		%c[d_blue] Х %c[ui_gray_2] импортный\n
		%c[d_blue] Х %c[ui_gray_2] быстрое использование (шприц)\n
		</text>
	</string>
	<string id="st_bandage">
		<text>Ѕинт</text>
	</string>
	<string id="st_bandage_descr">
		<text>јсептический бинт дл€ остановки кровотечени€ и предотвращени€ попадани€ в рану инфекции. ѕри обычном кровотечении позвол€ет перев€зать рану, при артериальном - перет€нуть артерию.\n \n
		%c[ui_gray_3]’ј–ј “≈–»—“» »:\n
		%c[d_blue] Х %c[ui_gray_2] останавливает кровотечение\n
		%c[d_blue] Х %c[ui_gray_2] изделие первой помощи\n
		%c[d_blue] Х %c[ui_gray_2] быстрое использование (лейкопластырь)\n
		</text>
	</string>
	
	<string id="st_bandage_army">
		<text>јрмейский бинт</text>
	</string>
	<string id="st_bandage_army_descr">
		<text>јсептический армейский бинт дл€ остановки кровотечени€ и предотвращени€ попадани€ в рану инфекции. ѕри обычном кровотечении позвол€ет перев€зать рану, при артериальном - перет€нуть артерию.\n \n
		%c[ui_gray_3]’ј–ј “≈–»—“» »:\n
		%c[d_blue] Х %c[ui_gray_2] останавливает кровотечение\n
		%c[d_blue] Х %c[ui_gray_2] изделие первой помощи\n
		%c[d_blue] Х %c[ui_gray_2] быстрое использование (лейкопластырь)\n
		</text>
	</string>
	
	<string id="st_drug_coagulant">
		<text>ЂЅарвинокї (ѕривозной)</text>
	</string>
	<string id="st_drug_coagulant_descr">
		<text>”краинский Ђ¬икасолї - синтетический аналог витамина  . ќсновное действие заключаетс€ в повышении свЄртываемости крови. ѕользуетс€ спросом среди сталкеров, поскольку позвол€ет организму быстрее рубцевать рваные раны. ќбладает продолжительным действием. ѕриЄм по 2 таблетки.\n \n
		%c[ui_gray_3]’ј–ј “≈–»—“» »:\n
		%c[d_blue] Х %c[ui_gray_2] останавливает кровотечение\n
		%c[d_red] Х %c[ui_gray_2] вызывает слабое головокружение\n</text>
	</string>
	
	<string id="st_drug_anabiotic">
		<text>јнабиотик</text>
	</string>
	<string id="st_drug_anabiotic_descr">
		<text>Ёкспериментальный препарат, разработанный дл€ научно-исследовательских групп, действующих в «оне. ¬ход€щий в формулу препарата тетрадотоксин, известный как Ђпорошок зомбиї, вызывает полный паралич центральной нервной системы; предположительно, это может обеспечить выживание вне укрыти€ во врем€ выброса. —пуст€ шесть лет полевых испытаний большинство рассудительных сталкеров теперь держит при себе парочку таких на случай внезапных выбросов.\n \n
		%c[ui_gray_3]’ј–ј “≈–»—“» »:\n
		%c[0,153,255,255] Х %c[ui_gray_2] медикамент\n
		%c[d_blue] Х %c[ui_gray_2] сделан в «оне\n
		%c[d_red] Х %c[ui_gray_2] вызывает временные провалы в пам€ти\n</text>
	</string>
	
	<string id="st_drug_psy_blockade">
		<text>Ђѕси-блокадаї</text>
	</string>
	<string id="st_drug_psy_blockade_descr">
		<text>Ќаркотический препарат, блокирующий лавинообразные нервные импульсы. »нтересен побочный эффект: после приЄма препарата наблюдаетс€ кратковременное исчезновение каких-либо эмоций. ¬ «оне используетс€ дл€ противодействи€ аномальным пол€м повышенной пси-активности; за еЄ пределами применени€ не нашЄл. ќбладает продолжительным действием. ѕриЄм по 2 таблетки.\n \n
		%c[ui_gray_3]’ј–ј “≈–»—“» »:\n
		%c[d_blue] Х %c[ui_gray_2] медикамент\n
		%c[d_blue] Х %c[ui_gray_2] пси-защита\n
		%c[d_red] Х %c[ui_gray_2] вызывает сильнейшее головокружение\n
		</text>
	</string>
	
	<string id="st_drug_antidot">
		<text>јнтидот</text>
	</string>
	<string id="st_drug_antidot_descr">
		<text>ѕрепарат Ђјнтитоксикант »ѕ2ї представл€ет собой комплекс антидотов: метоклопрамида, пиридоксина, тиамина, рибоксина и других. ¬водит в кровь вещества, способные разлагать белковые €ды, а также абсорбенты синтетических €дов. ќсобой попул€рностью не пользуетс€, поскольку большинство сталкеров больше полагаютс€ на противогаз и комбинезон. “ем не менее есть ещЄ те сталкеры, которые имеют несколько припр€танных упаковок этого препарата на чрезвычайный случай. ќбладает продолжительным действием. ѕриЄм по 1 капсуле.\n \n
		%c[ui_gray_3]’ј–ј “≈–»—“» »:\n
		%c[d_blue] Х %c[ui_gray_2] медикамент\n
		%c[d_blue] Х %c[ui_gray_2] химзащита\n
		%c[d_red] Х %c[ui_gray_2] вызывает слабое головокружение\n</text>
	</string>
	
	<string id="st_drug_booster">
		<text>Ђ√еркулесї</text>
	</string>
	<string id="st_drug_booster_descr">
		<text>ќсновной компонент - искусственно созданный стероид, по химическому составу сходный с тестостероном. ѕримен€етс€ сталкерами в долгих переходах дл€ повышени€ порога утомл€емости мышц. ѕомогает значительно увеличить переносимый вес. ѕрепарат длительного действи€.\n \n
		%c[ui_gray_3]’ј–ј “≈–»—“» »:\n
		%c[d_blue] Х %c[ui_gray_2] напиток\n
		%c[d_blue] Х %c[ui_gray_2] импортный\n
		%c[d_blue] Х %c[ui_gray_2] медикамент\n
		%c[d_blue] Х %c[ui_gray_2] слабый отрезвл€ющий эффект\n
		</text>
	</string>
	
	<string id="st_drug_radioprotector">
		<text>–адиопротектор</text>
	</string>
	<string id="st_drug_radioprotector_descr">
		<text>–адиопротектор Ђ»ндралин-Ѕ190ї входил в состав личных аптечек работников јЁ—. ѕо€вилс€ в «оне в качестве замены излишне токсичному цистамину гидрохлорида (–—1). ”меньшает воздействие гамма-излучени€ на ткани живого организма. ƒанный препарат желательно примен€ть превентивно, то есть до облучени€, поскольку он не оказывает мгновенного эффекта. ќбладает продолжительным действием. ѕриЄм по 1 капсуле.\n \n
		%c[ui_gray_3]’ј–ј “≈–»—“» »:\n
		%c[d_blue] Х %c[ui_gray_2] медикамент\n
		%c[d_blue] Х %c[ui_gray_2] радиозащита\n
		%c[d_red] Х %c[ui_gray_2] лЄгкое головокружение\n
		</text>
	</string>
	
	<string id="st_akvatab">
		<text>»бупрофен</text>
	</string>
	<string id="st_akvatab_descr">
		<text>Ќестероидный противовоспалительный препарат из группы производных пропионовой кислоты, обладает болеутол€ющим и жаропонижающим действием. ќбщие побочные эффекты включают изжогу и сыпь.\n \n
		%c[ui_gray_3]’ј–ј “≈–»—“» »:\n
		%c[d_blue] Х %c[ui_gray_2] обезболивающие \n
		%c[d_purple] Х %c[ui_gray_2] средний бонус сопротивлени€ к урону\n
		%c[d_red] Х %c[ui_gray_2] медленное использование (диспергируемые таблетки)\n
		</text>
	</string>
	
	<string id="st_medkit_ai1">
		<text>Grizzly</text>
	</string>
	<string id="st_medkit_ai1_descr">
		<text>“уристическа€ аптечка Grizzly Medical Kit считаетс€ одним из лучших комплектов первой помощи. —одержит все необходимое дл€ оказани€ своевременной медпомощи в экстремальных услови€х.\n \n
		%c[ui_gray_3]—ќƒ≈–∆»ћќ≈:\n
		%c[d_cyan] Х %c[default] бинты\n
		%c[d_cyan] Х %c[default] аптечка Salewa\n
		%c[d_cyan] Х %c[default] шина на руку\n
		%c[d_cyan] Х %c[default] шина на ногу\n
		%c[d_cyan] Х %c[default] антибиотики\n
		%c[d_cyan] Х %c[default] анабиотик\n
		%c[d_cyan] Х %c[default] »бупрофен\n
		%c[d_cyan] Х %c[default] Ѕарвинок\n
		%c[ui_gray_3]’ј–ј “≈–»—“» »:\n
		%c[d_blue] Х %c[ui_gray_2] хранилище дл€ медицинского снар€жени€\n</text>
	</string>
	
	<string id="st_medkit_ai2">
		<text> ейс дл€ медикаментов</text>
	</string>
	<string id="st_medkit_ai2_descr">
		<text> ейс дл€ компактного хранени€ медикаментов.\n \n
		%c[ui_gray_3]—ќƒ≈–∆»ћќ≈:\n
		%c[d_cyan] Х %c[default] морфин\n
		%c[d_cyan] Х %c[default] адреналин\n
		%c[d_cyan] Х %c[default] боевой стимул€тор SJ1\n
		%c[d_cyan] Х %c[default] боевой стимул€тор SJ6\n
		%c[d_cyan] Х %c[default] «агустин\n
		%c[d_cyan] Х %c[default] ѕропитал\n
		%c[d_cyan] Х %c[default] eTG-c\n
		%c[ui_gray_3]’ј–ј “≈–»—“» »:\n
		%c[d_blue] Х %c[ui_gray_2] хранилище дл€ медицинского снар€жени€\n</text>
	</string>
	
	<string id="st_medkit_ai3">
		<text>—тара€ аптечка</text>
	</string>
	<string id="st_medkit_ai3_descr">
		<text>Ёта стара€ наплечна€ сумка содержит все необходимое дл€ оказани€ первой помощи в суровых услови€х зоны. ќт радиационной до химической или пси защиты. “акже имеютс€ хирургические инструменты и военные бинты.\n \n
		%c[ui_gray_3]—ќƒ≈–∆»ћќ≈:\n
		%c[d_cyan] Х %c[default] армейский бинт\n
		%c[d_cyan] Х %c[default] аптечка ј»-2\n
		%c[d_cyan] Х %c[default] хирургические инструменты\n
		%c[d_cyan] Х %c[default] противорадиационный препарат\n
		%c[d_cyan] Х %c[default] радиопротектор\n
		%c[d_cyan] Х %c[default] антидот\n
		%c[d_cyan] Х %c[default] Ђѕси-блокадаї\n
		%c[d_cyan] Х %c[default] вазелин\n
		%c[d_cyan] Х %c[default] таблетки кофеина\n
		%c[ui_gray_3]’ј–ј “≈–»—“» »:\n
		%c[d_blue] Х %c[ui_gray_2] хранилище дл€ медицинского снар€жени€\n</text>
	</string>
	
	<string id="st_analgetic">
		<text>ћедицинские отходы</text>
	</string>
	<string id="st_analgetic_descr">
		<text>ќпасные медицинские отходы. ѕотому что в услови€х зоны использование медикаментов обычное дело. ѕосле чего остаетс€ много отходов во всей зоне.\n \n
		%c[ui_gray_3]’ј–ј “≈–»—“» »:\n
		%c[d_blue] Х %c[ui_gray_2] медицинские отходы\n
		%c[d_red] Х %c[ui_gray_2] высокий шанс поранитьс€ или получить инфекцию\n
		</text>
	</string>
	
	<string id="st_jgut_zhgut">
		<text>CMS</text>
	</string>
	<string id="st_jgut_descr">
		<text> омпактный хирургический набор дл€ оказани€ первой помощи при пулевых ранени€х и прочих серьезных травмах и ранах.\n \n
		%c[ui_gray_3]’ј–ј “≈–»—“» »:\n
		%c[d_blue] Х %c[ui_gray_2] хирургические инструменты\n
		%c[d_blue] Х %c[ui_gray_2] импортный\n
		%c[d_blue] Х %c[ui_gray_2] высокого качества\n
		%c[d_blue] Х %c[ui_gray_2] набор дл€ посто€нного восстановлени€ головы и торса\n
		%c[d_red] Х %c[ui_gray_2] медленное использование (полевой комплект)\n
		</text>
	</string>
	
	<string id="st_surginst">
		<text>’ирургические инструменты</text>
	</string>
	<string id="st_surginst_descr">
		<text>Ќебольша€ вариаци€ хирургических инструментов распространенных в зоне. ќни используютс€ дл€ создани€ Surv12 и набора CMS. ћожно использовать напр€мую, но дл€ этого нужен бинт так как инструменты не стерильны. “аким образом, их можно использовать только один раз.\n \n
		%c[ui_gray_3]’ј–ј “≈–»—“» »:\n
		%c[d_blue] Х %c[ui_gray_2] маленький набор дл€ посто€нного восстановлени€ всех частей тела\n
		%c[d_blue] Х %c[ui_gray_2] предмет дл€ создани€\n
		%c[d_blue] Х %c[ui_gray_2] хирургический предмет\n
		%c[d_blue] Х %c[ui_gray_2] импортные\n
		%c[d_blue] Х %c[ui_gray_2] высокого качества\n
		</text>
	</string>
	
	<string id="st_yadylin">
		<text>јнтибиотики</text>
	</string>
	<string id="st_yadylin_descr">
		<text> омбинированный антибиотик широкого спектра действи€, использующийс€ дл€ лечени€ бактериальных инфекционных заболеваний.\n \n
		%c[ui_gray_3]’ј–ј “≈–»—“» »:\n
		%c[d_blue] Х %c[ui_gray_2] медикамент\n
		%c[d_blue] Х %c[ui_gray_2] импортный\n
		%c[d_blue] Х %c[ui_gray_2] агонистическое вли€ние\n
		%c[d_red] Х %c[ui_gray_2] вызывает кратковременное помутнение сознани€\n
		%c[d_red] Х %c[ui_gray_2] медленное использование (диспергируемые таблетки)\n
		%c[d_purple] Х %c[ui_gray_2] небольшой бонус к сопротивлению урону\n
		</text>
	</string>
	
		<string id="st_medkit">
		<text>IFAK</text>
	</string>
	<string id="st_medkit_descr">
		<text>IFAK - это индивидуальный медицинский набор-аптечка, который выдаетс€ военнослужащим при несении службы. ќфициальна€ аптечка U.S. Marine Corps IFAK (»ндивидуальный медицинский набор  орпуса ћорской пехоты —Ўј). ѕоследнее, третье поколение (gen3), наиболее продуманное и самое богатое по комплектации.\n \n
		%c[ui_gray_3]’ј–ј “≈–»—“» »:\n
		%c[d_blue] Х %c[ui_gray_2] военное изделие\n
		%c[d_red] Х %c[ui_gray_2] медленное использование (полевой комплект)\n
		%c[d_red] Х %c[ui_gray_2] восстанавливает здоровье длительное врем€\n
		</text>
	</string>
	
	<string id="st_medkit_cheese">
		<text>ј»-2</text>
	</string>
	<string id="st_medkit_cheese_descr">
		<text>Ѕыла разработана как штатное средство первой медицинской помощи дл€ силовых структур и сил гражданской обороны в ———–. ¬ услови€х тотального военного конфликта с применением оружи€ массового поражени€ должна была быть роздана гражданскому населению в зонах, близких к очагам поражени€.\n \n
		%c[ui_gray_3]’ј–ј “≈–»—“» »:\n
		%c[d_blue] Х %c[ui_gray_2] военное изделие\n
		%c[d_purple] Х %c[ui_gray_2] быстрое использование (полевой комплект)\n
		%c[d_red] Х %c[ui_gray_2] восстанавливает здоровье длительное врем€\n
		</text>
	</string>
	
	<string id="st_medkit_army">
		<text>јвтомобильна€ аптечка</text>
	</string>
	<string id="st_medkit_army_descr">
		<text> ак и огнетушитель, автомобильна€ аптечка €вл€етс€ очень необходимым и важным средством защиты в экстренной ситуации на дороге. “акже содержит средства дл€ остановки кровотечений.\n \n
		%c[ui_gray_3]’ј–ј “≈–»—“» »:\n
		%c[d_red] Х %c[ui_gray_2] медленное использование (полевой комплект)\n
		%c[d_purpl] Х %c[ui_gray_2] восстанавливает здоровье длительное врем€\n
		</text>
	</string>
	
	<string id="st_medkit_science">
		<text>Salewa</text>
	</string>
	<string id="st_medkit_science_descr">
		<text>јптечка, содержаща€ спасательную термонакидку, разнообразные перев€зочные материалы и инструменты.\n \n
		%c[ui_gray_3]’ј–ј “≈–»—“» »:\n
		%c[d_blue] Х %c[ui_gray_2] ценна€\n
		%c[d_blue] Х %c[ui_gray_2] высокого качества\n
		%c[d_red] Х %c[ui_gray_2] медленное использование (полевой комплект)\n
		%c[d_red] Х %c[ui_gray_2] восстанавливает здоровье длительное врем€\n
		</text>
	</string>
	
	<string id="st_glucose_s">
		<text>ћала€ инъекци€ глюкозы</text>
	</string>
	<string id="st_glucose_s_descr">
		<text>»нъекци€ глюкозы используетс€ в т€жЄлых случа€х диабета - гипогликемии. Ќо сталкеры используют еЄ в качестве стимул€тора - мгновенное повышение углеводов в организме вызывает быстрое повышение энергии. »з-за удобства поставки и быстроты применени€ инъекцию можно использовать в боевой обстановке, что делает данный стимул€тор хорошим средством ускорени€ заживлени€ ран.\n \n
		%c[ui_gray_3]’ј–ј “≈–»—“» »:\n
		%c[d_blue] Х %c[ui_gray_2] медикамент\n
		%c[d_blue] Х %c[ui_gray_2] импортна€\n
		%c[d_blue] Х %c[ui_gray_2] быстрое использование (шприц)\n																																									   
		</text>
	</string>
	
	<string id="st_glucose">
		<text>Ѕольша€ инъекци€ глюкозы</text>
	</string>
	<string id="st_glucose_descr">
		<text>»нъекци€ глюкозы используетс€ в т€жЄлых случа€х диабета - гипогликемии. Ќо сталкеры используют еЄ в качестве стимул€тора - мгновенное повышение углеводов в организме вызывает быстрое повышение энергии. »з-за удобства поставки и быстроты применени€ инъекцию можно использовать в боевой обстановке, что делает данный стимул€тор хорошим средством ускорени€ заживлени€ ран. —одержит большую дозу препарата.\n \n
		%c[ui_gray_3]’ј–ј “≈–»—“» »:\n
		%c[d_blue] Х %c[ui_gray_2] медикамент\n
		%c[d_blue] Х %c[ui_gray_2] импортна€\n
		%c[d_blue] Х %c[ui_gray_2] быстрое использование (шприц)\n																																					   
		</text>
	</string>
	
	<string id="st_stim_impro">
		<text>Ѕоевой стимул€тор SJ1</text>
	</string>
	<string id="st_stim_impro_descr">
		<text>Ѕоевой стимул€тор. »спользуетс€ дл€ увеличени€ силы и выносливости перед боем. ”меньшает ощущение боли. –азрешен к применению бойцами спецподразделений. –азработан Svarog Test Labs, с маркировкой SJ1. »меет побочные эффекты.\n \n
		%c[ui_gray_3]’ј–ј “≈–»—“» »:\n
		%c[d_blue] Х %c[ui_gray_2] медикамент\n
		%c[d_blue] Х %c[ui_gray_2] мпортный\n
		%c[d_blue] Х %c[ui_gray_2] военное изделие\n
		%c[d_blue] Х %c[ui_gray_2] быстрое использование (шприц)\n
		%c[d_purple] Х %c[ui_gray_2] хороший бонус к сопротивлению урону\n</text>
	</string>
	
	<string id="st_stim_military">
		<text>Ѕоевой стимул€тор SJ6</text>
	</string>
	<string id="st_stim_military_descr">
		<text>Ѕоевой стимул€тор. »спользуетс€ дл€ расширени€ способностей организма перед боем. –азрешен к применению бойцами спецподразделений. –азработан Svarog Test Labs, с маркировкой SJ6. »меет побочные эффекты.\n \n
		%c[ui_gray_3]’ј–ј “≈–»—“» »:\n
		%c[d_blue] Х %c[ui_gray_2] медикамент\n
		%c[d_blue] Х %c[ui_gray_2] мпортный\n
		%c[d_blue] Х %c[ui_gray_2] военное изделие\n
		%c[d_blue] Х %c[ui_gray_2] быстрое использование (шприц)\n
		%c[d_purple] Х %c[ui_gray_2] хороший бонус к сопротивлению урону\n
		%c[d_purple] Х %c[ui_gray_2] бонус к выносливости\n</text>
	</string>
	
	<string id="st_stim_scientic">
		<text>ѕропитал</text>
	</string>
	<string id="st_stim_scientic_descr">
		<text>¬оенный препарат. —тимулирует процессы регенерации, за счет усилени€ биосинтеза пуриновых и пиримидиновых оснований, –Ќ , функциональных и ферментативных клеточных элементов. ѕовышает метаболизм, здоровье и жизнеспособность. »меет длительные побочные эффекты. –азрешено использовать только военным врачам и фельдшерам.\n \n
		%c[ui_gray_3]’ј–ј “≈–»—“» »:\n
		%c[d_blue] Х %c[ui_gray_2] медикамент\n
		%c[d_blue] Х %c[ui_gray_2] импортна€\n
		%c[d_blue] Х %c[ui_gray_2] высокого качества\n
		%c[d_blue] Х %c[ui_gray_2] быстрое использование (шприц)\n
		%c[d_purple] Х %c[ui_gray_2] быстро восстанавливает здоровье\n</text>
	</string>
	
	<string id="st_sleepingpills">
		<text>“аблетки 027 R</text>
	</string>
	<string id="st_sleepingpills_descr">
		<text>”паковка таблеток алпразолама 0,25 мг, также известных как 027 R. јлпразолам известен среди химиков своей способностью уменьшать тревожность,†депрессию† и панические расстройства. Ѕесценно дл€ всех, кто исследует янтарь, –адар, –ыжий лес или любую из подземных лабораторий. ѕобочные эффекты включают сонливость. Ћучше всего запивать водой, но некоторые сталкеры его как замену кофеину.\n \n
		%c[ui_gray_3]’ј–ј “≈–»—“» »:\n
		%c[d_blue] Х %c[ui_gray_2] медикамент\n
		%c[d_blue] Х %c[ui_gray_2] пси-защита\n
		</text>
	</string>
	
	<string id="st_cocaine">
		<text> окаин</text>
	</string>
	<string id="st_cocaine_descr">
		<text>Ќебольшой алюминиевый кейс, содержащий дозы кокаина и инструменты дл€ его инъекций.  окаин €вл€етс€ мощным стимул€тором нервной системы. ≈го действие длитс€ от 15-30 минут до часа, в зависимости от места введени€ инъекции.  окаин повышает бдительность, чувство благополучи€ и эйфории, повышает энергию и длительную активность, ощущение компетентности и сексуальности. ‘изическа€ сила может быть увеличена на спортивных сост€зани€х, где требуютс€ длительное внимание и выносливость. Ѕеспокойство, параной€ и неугомонность также €вл€ютс€ частыми симптомами его применени€. ѕри чрезмерной дозировке наблюдаютс€ сотр€сени€, конвульсии и увеличенна€ температура тела. Ѕандиты часто нюхают этот препарат непосредственно перед штурмом баз и лагерей.\n \n
		%c[ui_gray_3]’ј–ј “≈–»—“» »:\n
		%c[d_blue] Х %c[ui_gray_2] стимул€тор\n
		%c[d_blue] Х %c[ui_gray_2] очень мощное отрезвл€ющее действие\n
		%c[d_blue] Х %c[ui_gray_2] небольшое восстановление здоровь€ при использовании\n
		</text>
	</string>
	
	<string id="st_adrenalin">
		<text>јдреналин</text>
	</string>
	<string id="st_adrenalin_descr">
		<text>—терильный одноразовый шприц с дозой адреналина - основного гормона мозгового вещества надпочечников. »спользуетс€ дл€ усилени€ физиологической реакции, св€занной с подготовкой всех мышц к повышенной активности. ¬ременно повышает силу, выносливость. —нимает ощущение боли.\n \n
		%c[ui_gray_3]’ј–ј “≈–»—“» »:\n
		%c[d_blue] Х %c[ui_gray_2] медикамент\n
		%c[d_blue] Х %c[ui_gray_2] импортный\n
		%c[d_blue] Х %c[ui_gray_2] высокое качество\n
		%c[d_blue] Х %c[ui_gray_2] быстрое использование (шприц)\n
		%c[d_purple] Х %c[ui_gray_2] сильное повышение выносливости\n
		%c[d_purple] Х %c[ui_gray_2] снижает утомл€емость\n
		</text>
	</string>
	
	<string id="st_morphine">
		<text>ћорфий</text>
	</string>
	<string id="st_morphine_descr">
		<text>—терильный одноразовый шприц с дозой морфи€ - сильного наркотического анальгетика, примен€ющегос€ дл€ сн€ти€ сильных болевых ощущений, как острых, так и хронических.\n \n
		%c[ui_gray_3]’ј–ј “≈–»—“» »:\n
		%c[d_blue] Х %c[ui_gray_2] медикамент\n
		%c[d_blue] Х %c[ui_gray_2] импортна€\n
		%c[d_blue] Х %c[ui_gray_2] высокое качество\n
		%c[d_blue] Х %c[ui_gray_2] быстрое использование (шприц)\n
		%c[d_blue] Х %c[ui_gray_2] очень сильное обезболивающее \n
		%c[d_purple] Х %c[ui_gray_2] больша€ бонус сопротивлени€ к урону\n
		%c[d_purple] Х %c[ui_gray_2] продолжительное действие\n
		%c[d_red] Х %c[ui_gray_2] вызывает временные провалы в пам€ти\n
		</text>
	</string>
	
	<string id="st_salicidic_acid">
		<text>eTG-Change</text>
	</string>
	<string id="st_salicidic_acid_descr">
		<text>ћощный стимул€тор процессов регенерации. ѕримен€етс€ дл€ быстрого восстановлени€ бойца после ранени€, либо во врем€ транспортировки т€жело раненных. –азрешено использовать только военным врачам и фельдшерам. »меет сильные побочные эффекты.\n \n
		%c[ui_gray_3]’ј–ј “≈–»—“» »:\n
		%c[d_blue] Х %c[ui_gray_2] медикамент\n
		%c[d_blue] Х %c[ui_gray_2] импортна€\n
		%c[d_blue] Х %c[ui_gray_2] высокое качество\n
		%c[d_blue] Х %c[ui_gray_2] быстрое использование (шприц)\n
		%c[d_purple] Х %c[ui_gray_2] сильное увеличение грузоподъемности\n
		</text>
	</string>
	
	<string id="st_caffeine">
		<text>“аблетки кофеина</text>
	</string>
	<string id="st_caffeine_descr">
		<text> офеин и бензоат натри€, которые заставл€ют работать нервную систему с максимально возможной эффективностью. ¬ значительной степени снижают сонливость. ѕриЄм по 2 таблетки.\n \n
		%c[ui_gray_3]’ј–ј “≈–»—“» »:\n
		%c[d_blue] Х %c[ui_gray_2] стимул€тор\n
		%c[d_blue] Х %c[ui_gray_2] мощное отрезвл€ющее действие\n
		</text>
	</string>
	
		<string id="st_antirad_cystamine">
		<text>јлюминиева€ шина (–уки)</text>
	</string>
	<string id="st_antirad_cystamine_descr">
		<text>ћедицинска€ шина, дл€ фиксации поражЄнных костей при оказании первой помощи.\n \n
		%c[ui_gray_3]’ј–ј “≈–»—“» »:\n
		%c[d_blue] Х %c[ui_gray_2] перва€ помощь при переломе рук\n
		%c[d_blue] Х %c[ui_gray_2] импортна€\n
		%c[d_blue] Х %c[ui_gray_2] быстро и надежно\n
		</text>
	</string>
	
	<string id="st_antibio_sulfad">
		<text>јнальгин</text>
	</string>
	<string id="st_antibio_sulfad_descr">
		<text>ѕростейшее и самое дешЄвое из известных обезболивающих.\n \n
		%c[ui_gray_3]’ј–ј “≈–»—“» »:\n
		%c[d_blue] Х %c[ui_gray_2] медикамент\n
		%c[d_blue] Х %c[ui_gray_2] обезболивающие \n
		%c[d_purple] Х %c[ui_gray_2] небольшой бонус к сопротивлению урону\n
		</text>
	</string>
	
	<string id="st_antibio_chlor">
		<text>ћедицинские отходы</text>
	</string>
	<string id="st_antibio_chlor_descr">
		<text>ќпасные медицинские отходы. ѕотому что в услови€х зоны использование медикаментов обычное дело. ѕосле чего остаетс€ много отходов во всей Pоне.\n \n
		%c[ui_gray_3]’ј–ј “≈–»—“» »:\n
		%c[d_blue] Х %c[ui_gray_2] медицинские отходы\n
		%c[d_red] Х %c[ui_gray_2] высокий шанс поранитьс€ или получить инфекцию\n
		</text>
	</string>
	
	<string id="st_antiemetic">
		<text>ћедицинские отходы</text>
	</string>
	<string id="st_antiemetic_descr">
		<text>ќпасные медицинские отходы. ѕотому что в услови€х зоны использование медикаментов обычное дело. ѕосле чего остаетс€ много отходов во всей Pоне.\n \n
		%c[ui_gray_3]’ј–ј “≈–»—“» »:\n
		%c[d_blue] Х %c[ui_gray_2] медицинские отходы\n
		%c[d_red] Х %c[ui_gray_2] высокий шанс поранитьс€ или получить инфекцию\n
		</text>
	</string>
	
	<string id="st_joint">
		<text> ос€к конопли</text>
	</string>
	<string id="st_joint_descr">
		<text>Ѕлагодар€ своему успокаивающему эффекту довольно попул€рен среди сталкеров, которые наход€тс€ на границах –ыжего леса, Ђ¬ыжигател€ї и прочих пси-установок.  ос€к успокоит нервы и поможет расслабитьс€ на некоторое врем€. ј в сочетании с алкоголем имеет просто отличное успокаивающее действие. ѕовышает чувство голода.\n \n
		%c[ui_gray_3]’ј–ј “≈–»—“» »:\n
		%c[d_blue] Х %c[ui_gray_2] стимул€тор\n
		%c[d_blue] Х %c[ui_gray_2] сделан в «оне\n
		%c[d_blue] Х %c[ui_gray_2] слабый отрезвл€ющий эффект\n
		</text>
	</string>
	
	<string id="st_rebirth">
		<text>«агустин</text>
	</string>
	<string id="st_rebirth_descr">
		<text>¬оенный препарат. »нгибирует активаторы профибринолизина и тормозит его превращение в фибринолизин. ¬ременно останавливает кровотечение и повышает устойчивость к новым. »меет побочные эффекты. ѕриводит к сильной дегидратации.\n \n
		%c[ui_gray_3]’ј–ј “≈–»—“» »:\n
		%c[d_blue] Х %c[ui_gray_2] медикамент\n
		%c[d_blue] Х %c[ui_gray_2] быстро останавливает кровотечение\n
		%c[d_blue] Х %c[ui_gray_2] быстрое использование (шприц)\n
		</text>
	</string>
	
	<string id="st_tetanus">
		<text>¬азелин</text>
	</string>
	<string id="st_tetanus_descr">
		<text>¬азелин - универсальна€ мазь, примен€ема€ везде, где требуютс€ водоизол€ционные или смазочные свойства, например, санобработка небольших царапин и ожогов, нанесение защитного покрыти€ на склонные к коррозии предметы или смазка механизмов, требующих не содержащих кислоты смазок.\n \n
		%c[ui_gray_3]’ј–ј “≈–»—“» »:\n
		%c[d_blue] Х %c[ui_gray_2] наружное использование\n
		%c[d_blue] Х %c[ui_gray_2] предмет дл€ ремонта, смазка \n
		%c[d_blue] Х %c[ui_gray_2] бонус защиты от ожогов \n
		%c[d_blue] Х %c[ui_gray_2] импортна€\n</text>
	</string>
	
	<string id="st_antirad_kalium">
		<text>Ўина (Ќоги)</text>
	</string>
	<string id="st_antirad_kalium_descr">
		<text>ћедицинска€ шина, дл€ фиксации поражЄнных костей при оказании первой помощи.\n \n
		%c[ui_gray_3]’ј–ј “≈–»—“» »:\n
		%c[d_blue] Х %c[ui_gray_2] перва€ помощь при переломе ног\n
		%c[d_blue] Х %c[ui_gray_2] импортна€\n
		%c[d_blue] Х %c[ui_gray_2] быстро и надежно\n
		</text>
	</string>
	
	<string id="st_marijuana">
		<text>ћарихуана</text>
	</string>
	<string id="st_marijuana_descr">
		<text>—амовыращенный гашиш.  урение травки - это попул€рное врем€препровождение в «оне, особенно в р€дах Ђ—вободыї, бойцы которой защищают ЂЅарьерї. ¬ «оне ќтчуждени€ марихуану можно купить мешками повсеместно. Ќекоторые полагают, что она, как препарат, помогает сохранить равновесие в голове и не свихнутьс€ от пси-воздействи€.\n \n
		%c[ui_gray_3]’ј–ј “≈–»—“» »:\n
		%c[d_blue] Х %c[ui_gray_2] стимул€тор\n
		%c[d_red] Х %c[ui_gray_2] медленное использование (вдыхание)\n
		%c[d_blue] Х %c[ui_gray_2] мощное отрезвл€ющее действие\n
		</text>
	</string>
	
</string_table>
