<?xml version="1.0" encoding="windows-1251"?>

<!--
	Уникальные прицелы для MP412 Rex
-->

<string_table>
	<string id="st_integrated_docter">
		<text>Прицел DOCTER</text>
	</string>
	<string id="st_integrated_docter_descr">
		<text>Доступно только через обновления.\n \n
		%c[d_purple] • %c[ui_gray_2] Увеличение: %c[ui_gray_1]отсутствует (коллиматор)\n
		%c[d_purple] • %c[ui_gray_2] Состояние: %c[ui_gray_1]отличное</text>
	</string>

    <string id="st_integrated_compact">
		<text>Компактный прицел</text>
	</string>
	<string id="st_integrated_compact_descr">
		<text>Доступно только через обновления.\n \n
		%c[d_purple] • %c[ui_gray_2] Увеличение: %c[ui_gray_1]отсутствует (коллиматор)\n
		%c[d_purple] • %c[ui_gray_2] Состояние: %c[ui_gray_1]отличное</text>
	</string>
</string_table>
